mcp_databend/__init__.py
mcp_databend/__main__.py
mcp_databend/env.py
mcp_databend/main.py
mcp_databend/safety.py
mcp_databend/server.py
mcp_databend-0.3.1.dist-info/licenses/LICENSE
mcp_databend-0.3.1.dist-info/METADATA
mcp_databend-0.3.1.dist-info/WHEEL
mcp_databend-0.3.1.dist-info/entry_points.txt
mcp_databend-0.3.1.dist-info/top_level.txt
mcp_databend-0.3.1.dist-info/RECORD
