Metadata-Version: 2.4
Name: mcp-databend
Version: 0.3.1
Summary: An MCP server for Databend.
Author-email: Databend Labs <z@databend.com>
Maintainer-email: Databend Labs <z@databend.com>
License-Expression: Apache-2.0
Project-URL: Homepage, https://github.com/databendlabs/mcp-databend
Project-URL: Repository, https://github.com/databendlabs/mcp-databend
Project-URL: Documentation, https://github.com/databendlabs/mcp-databend#readme
Project-URL: Issues, https://github.com/databendlabs/mcp-databend/issues
Keywords: mcp,databend,database,sql,ai
Classifier: Development Status :: 4 - Beta
Classifier: Intended Audience :: Developers
Classifier: Programming Language :: Python :: 3
Classifier: Programming Language :: Python :: 3.12
Classifier: Topic :: Database
Classifier: Topic :: Software Development :: Libraries :: Python Modules
Requires-Python: >=3.12
License-File: LICENSE
Requires-Dist: databend>=1.2.810
Requires-Dist: databend-driver>=0.27.3
Requires-Dist: fastmcp>=2.12.3
Requires-Dist: pyarrow>=21.0.0
Requires-Dist: python-dotenv>=1.1.0
Requires-Dist: lmdb>=1.5.1
Requires-Dist: sqlparse>=0.5.5
Dynamic: license-file
